pytls_ca/__init__.py
pytls_ca/crypt.py
pytls_ca/pytls.py
pytls_ca-0.0.6.dist-info/LICENSE
pytls_ca-0.0.6.dist-info/METADATA
pytls_ca-0.0.6.dist-info/WHEEL
pytls_ca-0.0.6.dist-info/entry_points.txt
pytls_ca-0.0.6.dist-info/RECORD
