Metadata-Version: 2.1
Name: pytls-ca
Version: 0.0.6
Summary: Quickly create self-signed TLS certificates for your local development environment.
Home-page: https://github.com/rodneyxr/pytls-ca
Author: Rodney Rodriguez
Requires-Python: >=3.8,<4.0
Classifier: Programming Language :: Python :: 3
Classifier: Programming Language :: Python :: 3.8
Classifier: Programming Language :: Python :: 3.9
Classifier: Programming Language :: Python :: 3.10
Classifier: Programming Language :: Python :: 3.11
Classifier: Programming Language :: Python :: 3.12
Requires-Dist: click (>=8.1.7,<9.0.0)
Requires-Dist: cryptography (>=42.0.2,<43.0.0)
Project-URL: Repository, https://github.com/rodneyxr/pytls-ca
